<?xml version="1.0" encoding="UTF-8"?>
<!DOCTYPE mapper PUBLIC "-//mybatis.org//DTD Mapper 3.0//EN" "http://mybatis.org/dtd/mybatis-3-mapper.dtd">
<mapper namespace="com.fui.cloud.dao.fui.shiro.RolesMapper">
  <resultMap id="BaseResultMap" type="com.fui.cloud.model.fui.Roles">
    <!--
      WARNING - @mbggenerated
      This element is automatically generated by MyBatis Generator, do not modify.
    -->
    <id column="id" jdbcType="BIGINT" property="id" />
    <result column="role_code" jdbcType="VARCHAR" property="roleCode" />
    <result column="role_name" jdbcType="VARCHAR" property="roleName" />
  </resultMap>
  <sql id="Base_Column_List">
    <!--
      WARNING - @mbggenerated
      This element is automatically generated by MyBatis Generator, do not modify.
    -->
    id, role_code, role_name
  </sql>
  <select id="selectByPrimaryKey" parameterType="java.lang.Long" resultMap="BaseResultMap">
    <!--
      WARNING - @mbggenerated
      This element is automatically generated by MyBatis Generator, do not modify.
    -->
    select 
    <include refid="Base_Column_List" />
    from fui_roles
    where id = #{id,jdbcType=BIGINT}
  </select>
  <delete id="deleteByPrimaryKey" parameterType="java.lang.Long">
    <!--
      WARNING - @mbggenerated
      This element is automatically generated by MyBatis Generator, do not modify.
    -->
    delete from fui_roles
    where id = #{id,jdbcType=BIGINT}
  </delete>
  <insert id="insert" parameterType="com.fui.cloud.model.fui.Roles" useGeneratedKeys="true">
    <!--
      WARNING - @mbggenerated
      This element is automatically generated by MyBatis Generator, do not modify.
    -->
    <selectKey keyProperty="id" resultType="Long" order="BEFORE">
      select case when max(id) is null then 1 else max(id)+1 end as "id" from fui_roles
    </selectKey>
    insert into fui_roles (id, role_code, role_name)
    values (#{id,jdbcType=BIGINT}, #{roleCode,jdbcType=VARCHAR}, #{roleName,jdbcType=VARCHAR}
  </insert>
  <insert id="insertSelective" parameterType="com.fui.cloud.model.fui.Roles">
    <!--
      WARNING - @mbggenerated
      This element is automatically generated by MyBatis Generator, do not modify.
    -->
    insert into fui_roles
    <trim prefix="(" suffix=")" suffixOverrides=",">
      <if test="id != null">
        id,
      </if>
      <if test="roleCode != null">
        role_code,
      </if>
      <if test="roleName != null">
        role_name,
      </if>
    </trim>
    <trim prefix="values (" suffix=")" suffixOverrides=",">
      <if test="id != null">
        #{id,jdbcType=BIGINT},
      </if>
      <if test="roleCode != null">
        #{roleCode,jdbcType=VARCHAR},
      </if>
      <if test="roleName != null">
        #{roleName,jdbcType=VARCHAR},
      </if>
    </trim>
  </insert>
  <update id="updateByPrimaryKeySelective" parameterType="com.fui.cloud.model.fui.Roles">
    <!--
      WARNING - @mbggenerated
      This element is automatically generated by MyBatis Generator, do not modify.
    -->
    update fui_roles
    <set>
      <if test="roleCode != null">
        role_code = #{roleCode,jdbcType=VARCHAR},
      </if>
      <if test="roleName != null">
        role_name = #{roleName,jdbcType=VARCHAR},
      </if>
    </set>
    where id = #{id,jdbcType=BIGINT}
  </update>
  <update id="updateByPrimaryKey" parameterType="com.fui.cloud.model.fui.Roles">
    <!--
      WARNING - @mbggenerated
      This element is automatically generated by MyBatis Generator, do not modify.
    -->
    update fui_roles
    set role_code = #{roleCode,jdbcType=VARCHAR},
      role_name = #{roleName,jdbcType=VARCHAR}
    where id = #{id,jdbcType=BIGINT}
  </update>
  <select id="findRolesByCode" parameterType="java.lang.String" resultMap="BaseResultMap">
    select
      <include refid="Base_Column_List"/>
    from fui_roles where role_code = #{roleCode}
  </select>
  <select id="getRolesList" parameterType="java.util.Map" resultMap="BaseResultMap">
    SELECT
      <include refid="Base_Column_List"/>
    FROM fui_roles WHERE 1 = 1
    <if test="roleCode != null">
      AND role_code LIKE '%${roleCode}%'
    </if>
    <if test="roleName != null">
      AND role_name LIKE '%${roleName}%'
    </if>
  </select>
  <select id="getUserRights" parameterType="java.lang.Long" resultType="java.lang.String">
    SELECT permission_id FROM fui_role_permissions WHERE role_id IN ( SELECT role_id FROM fui_user_roles WHERE user_id = #{userId,jdbcType=BIGINT} )
  </select>
  <select id="getRolesByUserId" parameterType="java.lang.Long" resultType="java.lang.String">
    SELECT role_code FROM fui_roles WHERE id IN ( SELECT role_id FROM fui_user_roles WHERE user_id = #{userId,jdbcType=BIGINT} )
  </select>
</mapper>